{
    "language": "Language",
    "title": "SHIFT - Smart Handler for Invigilation and Functional Timetables",
    "shortTitle": "SHIFT",
    "shiftAssigner": "Shift Assignment",
    "filePrint": "Print",
    "uploadShiftCsv": "Upload Shifts as CSV:",
    "selectRole": "Select Role:",
    "messukeskusSupervisors": "Messukeskus supervisors",
    "messukeskusItSupport": "Messukeskus IT support",
    "uploadPreview": "Upload and Preview",
    "showShiftsBySupervisor": "Show Shifts by Supervisor",
    "showShiftsByExams": "Show Shifts by Exams",
    "assignBreaks": "Assign Breaks",
    "csvExport": "CSV export",
    "exportShiftsToCsv": "Export Shifts to CSV",
    "examSupervisorsExport": "Exam supervisors export",
    "selectExam": "Select Exam:",
    "allExams": "All Exams",
    "selectHall": "Select Hall:",
    "allSupervisors": "All supervisors",
    "allByHalls": "All by Halls",
    "sortByHalls": "Sort by Halls",
    "exportSupervisorListsToPdf": "Export supervisorlists to PDF",
    "workScheduleExport": "Work schedule export",
    "exportWorkSchedulesToPdfs": "Export Work Schedules to Individual PDFs",
    "firstName": "First Name",
    "lastName": "Last Name",
    "languageSkill": "Language Skill",
    "previousExperience": "Previous Experience",
    "disqualifications": "Disqualifications",
    "totalShifts": "Total Shifts",
    "shiftDetails": "Shift Details",
    "shift": "Shift",
    "supervisorsAssigned": "Supervisors Assigned",
    "supervisorsByHall": "Supervisors by Hall",
    "actions": "Actions",
    "viewSupervisors": "View Supervisors",
    "viewStats": "View Statistics"
}